pretty_cli/__init__.py
mff_pretty_cli-0.2.2.dist-info/METADATA
mff_pretty_cli-0.2.2.dist-info/WHEEL
mff_pretty_cli-0.2.2.dist-info/licenses/LICENSE
mff_pretty_cli-0.2.2.dist-info/RECORD
