Metadata-Version: 2.4
Name: mff-pretty-cli
Version: 0.2.2
Summary: Simple helper to get pretty printing in the CLI.
Author-email: Marc Fraile <marc.fraile.fabrega@gmail.com>
License-Expression: MIT
License-File: LICENSE
Requires-Python: >=3.8
